LICENSE
README.rst
localtodo.py
setup.py
localtodo.egg-info/PKG-INFO
localtodo.egg-info/SOURCES.txt
localtodo.egg-info/dependency_links.txt
localtodo.egg-info/entry_points.txt
localtodo.egg-info/requires.txt
localtodo.egg-info/top_level.txt