Metadata-Version: 1.0
Name: localtodo
Version: 1.0
Summary: .gitignore local todo files, but sync them through Dropbox.
Home-page: https://github.com/miracle2k/localtodo
Author: Michael Elsdörfer
Author-email: michael@elsdoerfer.com
License: BSD
Platform: UNKNOWN
Classifier: Development Status :: 5 - Production/Stable
Classifier: Intended Audience :: Developers
Classifier: License :: OSI Approved :: BSD License
Classifier: Operating System :: OS Independent
Classifier: Programming Language :: Python
